livekit/__init__.py
livekit/plugins/__init__.py
livekit/plugins/induslabs/__init__.py
livekit/plugins/induslabs/log.py
livekit/plugins/induslabs/stt.py
livekit/plugins/induslabs/tts.py
livekit/plugins/induslabs/version.py
livekit_plugins_induslabs-0.0.3.dist-info/METADATA
livekit_plugins_induslabs-0.0.3.dist-info/WHEEL
livekit_plugins_induslabs-0.0.3.dist-info/RECORD
