Metadata-Version: 2.4
Name: livekit-plugins-induslabs
Version: 0.0.3
Summary: Agent Framework plugin for services using IndusLabs API.
Project-URL: Documentation, https://docs.induslabs.io
Project-URL: Website, https://induslabs.io/
Project-URL: Source, https://github.com/INDUS-AI-DEV/induslabs-livekit-plugins
Author-email: IndusLabs <support@induslabs.io>
License-Expression: MIT
Keywords: audio,induslabs,livekit,realtime,stt,tts,video,webrtc
Requires-Python: >=3.8
Requires-Dist: aiohttp>=3.9.0
Requires-Dist: induslabs>=0.0.4
Requires-Dist: livekit-agents[codecs]>=1.2.15
Requires-Dist: numpy>=1.26
Requires-Dist: webrtcvad>=2.0.10
